iris_hector_patino/VERSION
iris_hector_patino/__init__.py
iris_hector_patino/config.yml
iris_hector_patino/pipeline.py
iris_hector_patino/predict.py
iris_hector_patino/train_pipeline.py
iris_hector_patino/config/__init__.py
iris_hector_patino/config/core.py
iris_hector_patino/datasets/__init__.py
iris_hector_patino/datasets/train.csv
iris_hector_patino/processing/__init__.py
iris_hector_patino/processing/data_manager.py
iris_hector_patino/processing/features.py
iris_hector_patino/processing/validation.py
iris_hector_patino/trained_models/__init__.py
iris_hector_patino/trained_models/pipeline_model_output_v0.0.1.pkl
requirements/__init__.py
requirements/requirements.txt
requirements/test_requirements.txt
iris_hector_patino-0.0.2.dist-info/METADATA
iris_hector_patino-0.0.2.dist-info/WHEEL
iris_hector_patino-0.0.2.dist-info/top_level.txt
iris_hector_patino-0.0.2.dist-info/RECORD
