Metadata-Version: 2.1
Name: iris-hector-patino
Version: 0.0.2
Summary: IRIS MODEL ROTE
Home-page: UNKNOWN
Author: hectorpatino
Author-email: hectorpatino24@gmail.com
License: BSD-3
Platform: UNKNOWN
Classifier: License :: OSI Approved :: MIT License
Classifier: Programming Language :: Python
Classifier: Programming Language :: Python :: 3
Classifier: Programming Language :: Python :: 3.6
Classifier: Programming Language :: Python :: 3.7
Classifier: Programming Language :: Python :: 3.8
Classifier: Programming Language :: Python :: 3.9
Classifier: Programming Language :: Python :: Implementation :: CPython
Classifier: Programming Language :: Python :: Implementation :: PyPy
Requires-Python: >=3.6.0
Requires-Dist: alembic (==1.7.5)
Requires-Dist: atomicwrites (==1.4.0)
Requires-Dist: attrs (==21.4.0)
Requires-Dist: autopage (==0.4.0)
Requires-Dist: cliff (==3.10.0)
Requires-Dist: cmaes (==0.8.2)
Requires-Dist: cmd2 (==2.3.3)
Requires-Dist: colorama (==0.4.4)
Requires-Dist: colorlog (==6.6.0)
Requires-Dist: distlib (==0.3.4)
Requires-Dist: feature-engine (==1.2.0)
Requires-Dist: filelock (==3.4.2)
Requires-Dist: greenlet (==1.1.2)
Requires-Dist: importlib-metadata (==4.10.0)
Requires-Dist: importlib-resources (==5.4.0)
Requires-Dist: iniconfig (==1.1.1)
Requires-Dist: joblib (==1.1.0)
Requires-Dist: Mako (==1.1.6)
Requires-Dist: MarkupSafe (==2.0.1)
Requires-Dist: numpy (==1.22.0)
Requires-Dist: optuna (==2.10.0)
Requires-Dist: packaging (==21.3)
Requires-Dist: pandas (==1.3.5)
Requires-Dist: patsy (==0.5.2)
Requires-Dist: pbr (==5.8.0)
Requires-Dist: platformdirs (==2.4.1)
Requires-Dist: pluggy (==1.0.0)
Requires-Dist: prettytable (==3.0.0)
Requires-Dist: py (==1.11.0)
Requires-Dist: pydantic (==1.9.0)
Requires-Dist: pyparsing (==3.0.6)
Requires-Dist: pyperclip (==1.8.2)
Requires-Dist: pyreadline3 (==3.3)
Requires-Dist: pytest (==6.2.5)
Requires-Dist: python-dateutil (==2.8.2)
Requires-Dist: pytz (==2021.3)
Requires-Dist: PyYAML (==6.0)
Requires-Dist: scikit-learn (==1.0.2)
Requires-Dist: scipy (==1.7.3)
Requires-Dist: six (==1.16.0)
Requires-Dist: sklearn (==0.0)
Requires-Dist: SQLAlchemy (==1.4.29)
Requires-Dist: statsmodels (==0.13.1)
Requires-Dist: stevedore (==3.5.0)
Requires-Dist: strictyaml (==1.6.1)
Requires-Dist: threadpoolctl (==3.0.0)
Requires-Dist: toml (==0.10.2)
Requires-Dist: tox (==3.24.5)
Requires-Dist: tqdm (==4.62.3)
Requires-Dist: virtualenv (==20.13.0)
Requires-Dist: wcwidth (==0.2.5)
Requires-Dist: xgboost (==1.5.1)
Requires-Dist: zipp (==3.7.0)
